rlipy/SymDataProto_pb2.py
rlipy/__init__.py
rlipy/cusip.py
rlipy/datafeed.py
rlipy/datafeedPrice.py
rlipy/datafeedThread.py
rlipy/env.py
rlipy/excelServer.py
rlipy/filewatch.py
rlipy/ftp.py
rlipy/htmlmail.py
rlipy/logger.py
rlipy/moveoldfile.py
rlipy/nscc.py
rlipy/redisConn.py
rlipy/subscriptionManager.py
rlipy/symbology.py
rlipy/test.py
rlipy/timer.py
rlipy/tradedate.py
rlipy/util.py
rlipy/vexception.py
rlipy/zpub.py
rlipy/zpull.py
rlipy/zpush.py
rlipy/zreq.py
rlipy/zsub.py
rlipy-0.4.15.dist-info/METADATA
rlipy-0.4.15.dist-info/WHEEL
rlipy-0.4.15.dist-info/top_level.txt
rlipy-0.4.15.dist-info/RECORD
